lsp_tree_sitter/__init__.py
lsp_tree_sitter/_metainfo.py
lsp_tree_sitter/_version.py
lsp_tree_sitter/complete.py
lsp_tree_sitter/diagnose.py
lsp_tree_sitter/finders.py
lsp_tree_sitter/format.py
lsp_tree_sitter/misc.py
lsp_tree_sitter/schema.py
lsp_tree_sitter/utils.py
lsp_tree_sitter-0.1.1.dist-info/licenses/LICENSE
lsp_tree_sitter-0.1.1.dist-info/METADATA
lsp_tree_sitter-0.1.1.dist-info/WHEEL
lsp_tree_sitter-0.1.1.dist-info/top_level.txt
lsp_tree_sitter-0.1.1.dist-info/RECORD
